LICENSE
MANIFEST.in
README.md
pavement.py
setup.py
EAOS/algorithms.py
EAOS/benchmarks.py
EAOS/fnevaluator.py
EAOS/generators.py
EAOS/individual.py
EAOS/operators.py
EAOS/stats.py
EAOS.egg-info/PKG-INFO
EAOS.egg-info/SOURCES.txt
EAOS.egg-info/dependency_links.txt
EAOS.egg-info/requires.txt
EAOS.egg-info/top_level.txt