Metadata-Version: 1.1
Name: EAOS
Version: 0.0.1
Summary: Evolutionary Algorithms Suite
Home-page: http://github.com/jdvelasq/evolutionary-optimization-suite
Author: Juan D. Velasquez
Author-email: jdvelasq@unal.edu.co
License: MIT
Keywords: Optimization
Platform: any
Classifier: Development Status :: 3 - Alpha
Classifier: License :: OSI Approved :: MIT License
Classifier: Intended Audience :: Science/Research
Classifier: Intended Audience :: Education
Classifier: Programming Language :: Python :: 3
Classifier: Programming Language :: Python :: 3.6
Classifier: Programming Language :: Python :: 3.5
Classifier: Programming Language :: Python :: 3.6
Classifier: Programming Language :: Python :: 3.7
Classifier: Programming Language :: Python :: 3.8
Provides: EAOS
